pylorem/__init__.py
pylorem/lorem.json
pylorem/lorem.py
tests/__init__.py
tests/test_lorem_ipsum.py
pylorem-1.2.dist-info/LICENSE.txt
pylorem-1.2.dist-info/METADATA
pylorem-1.2.dist-info/WHEEL
pylorem-1.2.dist-info/top_level.txt
pylorem-1.2.dist-info/RECORD
