Metadata-Version: 2.1
Name: pylorem
Version: 1.2
Summary: A Python lorem ipsum generator
Home-page: https://github.com/Julian-Nash/pylorem
Author: Julian Nash
Author-email: julianjamesnash@gmail.com
License: UNKNOWN
Project-URL: Bug Tracker, https://github.com/Julian-Nash/pylorem
Project-URL: Documentation, https://github.com/Julian-Nash/pylorem
Project-URL: Source Code, https://github.com/Julian-Nash/pylorem
Keywords: lorem ipsum placeholder dummy text generator
Platform: UNKNOWN
Classifier: Intended Audience :: Developers
Classifier: License :: OSI Approved :: MIT License
Classifier: Programming Language :: Python :: 3.6
Classifier: Programming Language :: Python :: 3.7
Classifier: Programming Language :: Python :: 3.8
